rda_toolbox/__init__.py
rda_toolbox/experiment_classes.py
rda_toolbox/marimo.py
rda_toolbox/parser.py
rda_toolbox/plot.py
rda_toolbox/process.py
rda_toolbox/utility.py
rda_toolbox-0.1.13.dist-info/LICENSE
rda_toolbox-0.1.13.dist-info/METADATA
rda_toolbox-0.1.13.dist-info/WHEEL
rda_toolbox-0.1.13.dist-info/RECORD
