Metadata-Version: 2.1
Name: rda-toolbox
Version: 0.1.13
Summary: 
Home-page: https://github.com/Robotic-Discovery-of-Antiinfectives/rda-toolbox
Author: timoleistner
Author-email: leistner.timo@googlemail.com
Requires-Python: >=3.12,<4.0
Classifier: Programming Language :: Python :: 3
Classifier: Programming Language :: Python :: 3.12
Requires-Dist: altair (>=5.4.0,<6.0.0)
Requires-Dist: mkdocstrings-python (>=1.15.0,<2.0.0)
Requires-Dist: numpy (>=2.0.1,<3.0.0)
Requires-Dist: openpyxl (>=3.1.5,<4.0.0)
Requires-Dist: pandas (>=2.2.2,<3.0.0)
Requires-Dist: vl-convert-python (>=1.7.0,<2.0.0)
Project-URL: Documentation, https://robotic-discovery-of-antiinfectives.github.io/rda-toolbox/
Project-URL: Repository, https://github.com/Robotic-Discovery-of-Antiinfectives/rda-toolbox
